dbt_cloud/__init__.py
dbt_cloud/dbt_cloud.py
hooks/__init__.py
hooks/dbt_cloud_hook.py
operators/__init__.py
operators/dbt_cloud_run_job_operator.py
sensors/__init__.py
sensors/dbt_cloud_job_sensor.py
dbt_cloud_plugin-0.0.1.dist-info/LICENSE
dbt_cloud_plugin-0.0.1.dist-info/METADATA
dbt_cloud_plugin-0.0.1.dist-info/WHEEL
dbt_cloud_plugin-0.0.1.dist-info/top_level.txt
dbt_cloud_plugin-0.0.1.dist-info/RECORD
