Metadata-Version: 2.1
Name: dbt-cloud-plugin
Version: 0.0.1
Summary: DBT Cloud plugin for Airflow
Home-page: https://github.com/dwallace0723/dbt-cloud-plugin
Author: dwallace0723
Author-email: zacharybannor@gmail.com
License: UNKNOWN
Project-URL: Bug Tracker, https://github.com/dwallace0723/dbt-cloud-plugin
Platform: UNKNOWN
Classifier: Programming Language :: Python :: 3
Classifier: License :: OSI Approved :: MIT License
Classifier: Operating System :: OS Independent
Requires-Python: >=3.6
License-File: LICENSE
